objloader/__init__.py
objloader-0.2.0.dist-info/METADATA
objloader-0.2.0.dist-info/RECORD
objloader-0.2.0.dist-info/WHEEL
objloader-0.2.0.dist-info/top_level.txt
