Metadata-Version: 1.0
Name: objloader
Version: 0.2.0
Summary: ModernGL extension for loading obj files
Home-page: https://github.com/cprogrammer1994/objloader
Author: Szabolcs Dombi
Author-email: cprogrammer1994@gmail.com
License: MIT
Platform: any
